Camera.py
ConfigHandler.py
RtspClient.py
resthandle.py
api/APIHandler.py
api/__init__.py
api/alarm.py
api/device.py
api/display.py
api/image.py
api/network.py
api/ptz.py
api/recording.py
api/system.py
api/user.py
api/zoom.py
reolink_api-0.0.5.dist-info/LICENSE.md
reolink_api-0.0.5.dist-info/METADATA
reolink_api-0.0.5.dist-info/WHEEL
reolink_api-0.0.5.dist-info/top_level.txt
reolink_api-0.0.5.dist-info/RECORD
