Metadata-Version: 2.1
Name: reolink-api
Version: 0.0.5
Summary: Reolink Camera API written in Python 3.6
Home-page: https://github.com/Benehiko/ReolinkCameraAPI
Author: Benehiko
Author-email: 
License: GPL-3.0
Platform: UNKNOWN
Requires-Python: >=3.6.0
Requires-Dist: pillow
Requires-Dist: pyyaml
Requires-Dist: requests (>=2.18.4)
Requires-Dist: numpy
Requires-Dist: opencv-python
Requires-Dist: pysocks
